app/__init__.py
app/amazon_sp_api.py
app/cli.py
app/config.py
app/dingtalk_doc_reader.py
app/history_recorder.py
app/main.py
app/notifier.py
app/retry_strategy.py
app/selectors.py
app/site_configs.py
app/spider.py
app/terminal_ui.py
app/models/__init__.py
app/models/detection_result.py
app/models/monitor_item.py
app/models/res_record.py
app/notifiers/__init__.py
app/notifiers/batch_notifier.py
app/readers/__init__.py
app/readers/multi_sheet_reader.py
app/recorders/__init__.py
app/recorders/res_recorder.py
app/selectors/__init__.py
app/selectors/amazon_selectors.py
app/selectors/walmart_selectors.py
app/spiders/__init__.py
app/spiders/base_spider.py
app/spiders/dual_platform_spider.py
app/spiders/walmart_bot_handler.py
app/spiders/walmart_spider.py
walmart_monitor-0.1.5.dist-info/METADATA
walmart_monitor-0.1.5.dist-info/WHEEL
walmart_monitor-0.1.5.dist-info/entry_points.txt
walmart_monitor-0.1.5.dist-info/RECORD
