Metadata-Version: 2.4
Name: walmart-monitor
Version: 0.1.5
Summary: Walmart/Amazon 商品监控系统 - 支持多站点商品状态检测和钉钉通知
Project-URL: Homepage, https://github.com/yourusername/walmart-monitor
Project-URL: Repository, https://github.com/yourusername/walmart-monitor
Project-URL: Documentation, https://github.com/yourusername/walmart-monitor#readme
Author: Leo
License: MIT
Keywords: amazon,dingtalk,fastapi,monitor,spider,walmart
Classifier: Development Status :: 4 - Beta
Classifier: Environment :: Console
Classifier: Framework :: FastAPI
Classifier: Intended Audience :: Developers
Classifier: License :: OSI Approved :: MIT License
Classifier: Operating System :: OS Independent
Classifier: Programming Language :: Python :: 3
Classifier: Programming Language :: Python :: 3.9
Classifier: Programming Language :: Python :: 3.10
Classifier: Programming Language :: Python :: 3.11
Classifier: Programming Language :: Python :: 3.12
Classifier: Topic :: Internet :: WWW/HTTP :: Indexing/Search
Requires-Python: >=3.9
Requires-Dist: alibabacloud-dingtalk>=2.0.0
Requires-Dist: croniter>=2.0.0
Requires-Dist: dingtalkchatbot>=1.5.0
Requires-Dist: drissionpage>=4.0.0
Requires-Dist: fake-useragent>=1.4.0
Requires-Dist: fastapi>=0.100.0
Requires-Dist: filelock>=3.13.0
Requires-Dist: python-amazon-sp-api>=1.0.0
Requires-Dist: python-dotenv>=1.0.0
Requires-Dist: rich>=13.0.0
Requires-Dist: uvicorn[standard]>=0.23.0
Provides-Extra: dev
Requires-Dist: pytest-asyncio>=0.21.0; extra == 'dev'
Requires-Dist: pytest>=7.0.0; extra == 'dev'
Requires-Dist: ruff>=0.1.0; extra == 'dev'
